netintel_ocr/__init__.py
netintel_ocr/__main__.py
netintel_ocr/__version__.py
netintel_ocr/batch_processor.py
netintel_ocr/centralized_db.py
netintel_ocr/checkpoint.py
netintel_ocr/cli.py
netintel_ocr/cli_v2.py
netintel_ocr/config.py
netintel_ocr/config_manager.py
netintel_ocr/constants.py
netintel_ocr/dedup_manager.py
netintel_ocr/dedup_milvus_manager.py
netintel_ocr/dedup_utils.py
netintel_ocr/embedding_manager.py
netintel_ocr/hybrid_processor.py
netintel_ocr/hybrid_processor_backup.py
netintel_ocr/lancedb_schema_v0114.py
netintel_ocr/logging_utils.py
netintel_ocr/multi_diagram_processor.py
netintel_ocr/network_processor.py
netintel_ocr/ollama.py
netintel_ocr/optimized_processor.py
netintel_ocr/output_utils.py
netintel_ocr/pdf.py
netintel_ocr/pdf_utils.py
netintel_ocr/pipeline.py
netintel_ocr/processor.py
netintel_ocr/project_initializer.py
netintel_ocr/prompt_manager.py
netintel_ocr/query_engine.py
netintel_ocr/query_interface.py
netintel_ocr/storage_backend.py
netintel_ocr/timeout_utils.py
netintel_ocr/utils.py
netintel_ocr/vector_regenerator.py
netintel_ocr/api/__init__.py
netintel_ocr/api/main.py
netintel_ocr/api/server.py
netintel_ocr/api/middleware/__init__.py
netintel_ocr/api/middleware/auth.py
netintel_ocr/api/middleware/ratelimit.py
netintel_ocr/api/models/__init__.py
netintel_ocr/api/models/database.py
netintel_ocr/api/models/documents.py
netintel_ocr/api/models/jobs.py
netintel_ocr/api/models/search.py
netintel_ocr/api/routes/__init__.py
netintel_ocr/api/routes/database.py
netintel_ocr/api/routes/documents.py
netintel_ocr/api/routes/health.py
netintel_ocr/api/routes/jobs.py
netintel_ocr/api/routes/search.py
netintel_ocr/api/services/__init__.py
netintel_ocr/api/services/auth.py
netintel_ocr/api/services/database.py
netintel_ocr/api/services/database_service.py
netintel_ocr/api/services/document_service.py
netintel_ocr/api/services/job_service.py
netintel_ocr/api/services/queue.py
netintel_ocr-0.1.18.2.dist-info/METADATA
netintel_ocr-0.1.18.2.dist-info/WHEEL
netintel_ocr-0.1.18.2.dist-info/entry_points.txt
netintel_ocr-0.1.18.2.dist-info/top_level.txt
netintel_ocr-0.1.18.2.dist-info/RECORD
