Metadata-Version: 2.4
Name: netintel-ocr
Version: 0.1.18.2
Summary: Enterprise Document Intelligence Platform with High-Performance C++ Extensions, API v2, MCP, and Vector Search
Home-page: https://github.com/VisionMLNet/NetIntelOCR
Author: VisionML
Author-email: VisionML <info@visionml.net>
Maintainer-email: VisionML Team <support@visionml.net>
License: MIT
Project-URL: Homepage, https://github.com/VisionMLNet/NetIntelOCR
Project-URL: Issues, https://github.com/VisionMLNet/NetIntelOCR/issues
Project-URL: Changelog, https://github.com/VisionMLNet/NetIntelOCR/changelog.md
Keywords: ocr,document-intelligence,network-analysis,knowledge-graph,vector-search,milvus,falkordb,pykeen,api,mcp,c++,avx2,openmp
Classifier: Development Status :: 4 - Beta
Classifier: Intended Audience :: Developers
Classifier: Intended Audience :: Science/Research
Classifier: License :: OSI Approved :: MIT License
Classifier: Operating System :: OS Independent
Classifier: Programming Language :: Python :: 3
Classifier: Programming Language :: Python :: 3.10
Classifier: Programming Language :: Python :: 3.11
Classifier: Programming Language :: Python :: 3.12
Classifier: Programming Language :: C++
Classifier: Topic :: Scientific/Engineering :: Artificial Intelligence
Classifier: Topic :: Software Development :: Libraries :: Python Modules
Classifier: Topic :: Text Processing :: General
Requires-Python: >=3.10
Requires-Dist: pymupdf>=1.26.1
Requires-Dist: pillow>=11.2.1
Requires-Dist: opencv-python-headless>=4.5.0
Requires-Dist: numpy>=1.24.0
Requires-Dist: click>=8.1.0
Requires-Dist: typer>=0.9.0
Requires-Dist: tqdm>=4.67.1
Requires-Dist: pandas>=2.0.0
Requires-Dist: jsonschema>=4.0.0
Requires-Dist: pyyaml>=6.0.0
Requires-Dist: psutil>=5.9.0
Requires-Dist: requests>=2.31.0
Requires-Dist: ollama>=0.1.0
Requires-Dist: tomli>=2.0.0; python_version < "3.11"
Provides-Extra: kg
Requires-Dist: falkordb>=1.0.8; extra == "kg"
Requires-Dist: graphiti-core>=0.3.0; extra == "kg"
Requires-Dist: pykeen>=1.10.0; extra == "kg"
Requires-Dist: minirag-hku>=0.0.2; extra == "kg"
Requires-Dist: torch>=2.0.0; extra == "kg"
Requires-Dist: torchvision>=0.15.0; extra == "kg"
Requires-Dist: scikit-learn>=1.0.0; extra == "kg"
Requires-Dist: matplotlib>=3.5.0; extra == "kg"
Requires-Dist: seaborn>=0.11.0; extra == "kg"
Requires-Dist: plotly>=5.0.0; extra == "kg"
Requires-Dist: asyncio-redis>=0.16.0; extra == "kg"
Provides-Extra: vector
Requires-Dist: pymilvus>=2.3.0; extra == "vector"
Requires-Dist: qdrant-client>=1.7.0; extra == "vector"
Requires-Dist: chromadb>=0.4.0; extra == "vector"
Requires-Dist: lancedb>=0.5.0; extra == "vector"
Provides-Extra: api
Requires-Dist: fastapi>=0.100.0; extra == "api"
Requires-Dist: uvicorn[standard]>=0.23.0; extra == "api"
Requires-Dist: python-multipart>=0.0.6; extra == "api"
Requires-Dist: pyjwt>=2.8.0; extra == "api"
Provides-Extra: mcp
Requires-Dist: fastmcp>=0.1.0; extra == "mcp"
Requires-Dist: websockets>=12.0.0; extra == "mcp"
Provides-Extra: performance
Requires-Dist: cmake>=3.12; extra == "performance"
Requires-Dist: pybind11>=2.6.0; extra == "performance"
Requires-Dist: scikit-build>=0.11.0; extra == "performance"
Requires-Dist: numba>=0.58.0; extra == "performance"
Requires-Dist: cython>=3.0.0; extra == "performance"
Provides-Extra: dev
Requires-Dist: pytest>=6.0.0; extra == "dev"
Requires-Dist: pytest-cov>=2.10.0; extra == "dev"
Requires-Dist: pytest-asyncio>=0.21.0; extra == "dev"
Requires-Dist: pytest-benchmark>=4.0.0; extra == "dev"
Requires-Dist: black>=20.8b1; extra == "dev"
Requires-Dist: ruff>=0.1.0; extra == "dev"
Requires-Dist: mypy>=1.0.0; extra == "dev"
Provides-Extra: production
Requires-Dist: netintel-ocr[kg]; extra == "production"
Requires-Dist: netintel-ocr[vector]; extra == "production"
Requires-Dist: netintel-ocr[api]; extra == "production"
Requires-Dist: netintel-ocr[performance]; extra == "production"
Provides-Extra: cloud
Requires-Dist: netintel-ocr[vector]; extra == "cloud"
Requires-Dist: netintel-ocr[api]; extra == "cloud"
Requires-Dist: netintel-ocr[mcp]; extra == "cloud"
Requires-Dist: aioboto3>=12.0.0; extra == "cloud"
Requires-Dist: redis[hiredis]>=5.0.0; extra == "cloud"
Provides-Extra: all
Requires-Dist: netintel-ocr[kg]; extra == "all"
Requires-Dist: netintel-ocr[vector]; extra == "all"
Requires-Dist: netintel-ocr[api]; extra == "all"
Requires-Dist: netintel-ocr[mcp]; extra == "all"
Requires-Dist: netintel-ocr[performance]; extra == "all"
Requires-Dist: netintel-ocr[dev]; extra == "all"
Dynamic: author
Dynamic: home-page
Dynamic: requires-python
